[
  {
    "items": [
      {
        "id": "a4af8a1d-5de3-4182-bdae-07c0fac40a34",
        "name": "Homelander",
        "subtitle": "SOHARTH Homelander Oversized Tee",
        "price": 349,
        "image": "https://res.cloudinary.com/dopypifbu/image/upload/v1780240652/soharth/ksexk1vnvbes8p0sfdl7.jpg",
        "qty": 1,
        "size": "M"
      },
      {
        "id": "6cb2880a-562e-4496-bcc5-0b1d723805f5",
        "name": "MATRIX",
        "subtitle": "Technical Spacer Crepe / Cosmic Dust",
        "price": 450,
        "image": "https://res.cloudinary.com/dopypifbu/image/upload/v1780245495/soharth/skgd5jtpizveuu0zerpn.jpg",
        "qty": 1,
        "size": "M"
      }
    ],
    "subtotal": 799,
    "tax": 63.92,
    "total": 862.92,
    "id": "ORW42GKHF",
    "timestamp": "2026-06-06T07:55:51.791Z"
  },
  {
    "items": [
      {
        "id": "4",
        "name": "ECLIPSE OVERCOAT",
        "subtitle": "Flowing Technical Crepe / Obsidian",
        "price": 1890,
        "image": "/WhatsApp Image 2026-05-29 at 12.50.13 PM.jpeg",
        "qty": 1,
        "size": "M"
      },
      {
        "id": "e09dde92-ac99-4ecb-9de3-b5881b3e174a",
        "name": "FIST OF STEEL",
        "subtitle": "COTTON BLEND",
        "price": 349,
        "image": "https://res.cloudinary.com/dopypifbu/image/upload/v1780239635/soharth/qayb5vgu4udc4kgv4ywd.jpg",
        "qty": 1,
        "size": "S"
      },
      {
        "id": "e09dde92-ac99-4ecb-9de3-b5881b3e174a",
        "name": "FIST OF STEEL",
        "subtitle": "COTTON BLEND",
        "price": 349,
        "image": "https://res.cloudinary.com/dopypifbu/image/upload/v1780239635/soharth/qayb5vgu4udc4kgv4ywd.jpg",
        "qty": 1,
        "size": "L"
      }
    ],
    "subtotal": 2588,
    "tax": 207.04,
    "total": 2795.04,
    "id": "F1F3B35BM",
    "timestamp": "2026-06-01T14:23:38.400Z",
    "orderStatus": "Confirmed"
  }
]